simple_youtube_api/__init__.py
simple_youtube_api/simple_youtube_api.py
simple_api_youtube-0.0.1.dist-info/METADATA
simple_api_youtube-0.0.1.dist-info/WHEEL
simple_api_youtube-0.0.1.dist-info/top_level.txt
simple_api_youtube-0.0.1.dist-info/RECORD
