Metadata-Version: 2.1
Name: simple-api-youtube
Version: 0.0.1
Summary: basic youtube api.
Home-page: UNKNOWN
Author: Real72
Author-email: real4ik.games@gmail.com
License: UNKNOWN
Platform: UNKNOWN
Classifier: Intended Audience :: Developers
Classifier: Programming Language :: Python :: 3
Classifier: Operating System :: Unix
Classifier: Operating System :: MacOS :: MacOS X
Classifier: Operating System :: Microsoft :: Windows
Requires-Dist: google-api-python-client
Requires-Dist: loguru
